{
    "type": "minecraft:crafting_shaped",
    "category": "equipment",
    "pattern": ["XX", "XO", " O"],
    "key": {
        "X": { "item": "minecraft:emerald" },
        "O": { "item": "minecraft:stick" }
    },
    "result": {
        "id": "minecraft:diamond_axe",
        "components": {
            "minecraft:max_damage": 1650,
            "custom_model_data": 1,
            "custom_name": "[{'text':'Emerald Axe','italic':false,'color':white}]",
            "minecraft:attribute_modifiers": {
                "modifiers": [
                    {
                        "type": "minecraft:generic.attack_damage",
                        "uuid": [12, 65416, 5146, 21],
                        "name": "dmg",
                        "amount": 10,
                        "operation": "add_value",
                        "slot": "mainhand"
                    },
                    {
                        "type": "minecraft:generic.attack_speed",
                        "uuid": [654, 654, 654, 321],
                        "name": "atck speed",
                        "amount": -3.11,
                        "operation": "add_value",
                        "slot": "mainhand"
                    }
                ]
            }
        }
    }
}
